examples/__init__.py
examples/creator_query.py
examples/simple_query.py
reservoir_sdk/__init__.py
reservoir_sdk/client.py
reservoir_sdk-0.1.0.dist-info/licenses/LICENSE
reservoir_sdk-0.1.0.dist-info/METADATA
reservoir_sdk-0.1.0.dist-info/WHEEL
reservoir_sdk-0.1.0.dist-info/top_level.txt
reservoir_sdk-0.1.0.dist-info/RECORD
